spinn_front_end_common/__init__.py
spinn_front_end_common/_version.py
spinn_front_end_common/py.typed
spinn_front_end_common/abstract_models/__init__.py
spinn_front_end_common/abstract_models/abstract_can_reset.py
spinn_front_end_common/abstract_models/abstract_generates_data_specification.py
spinn_front_end_common/abstract_models/abstract_has_associated_binary.py
spinn_front_end_common/abstract_models/abstract_rewrites_data_specification.py
spinn_front_end_common/abstract_models/abstract_send_me_multicast_commands_vertex.py
spinn_front_end_common/abstract_models/abstract_supports_bit_field_generation.py
spinn_front_end_common/abstract_models/abstract_supports_bit_field_routing_compression.py
spinn_front_end_common/abstract_models/abstract_supports_database_injection.py
spinn_front_end_common/abstract_models/abstract_vertex_with_dependent_vertices.py
spinn_front_end_common/abstract_models/has_custom_atom_key_map.py
spinn_front_end_common/abstract_models/live_output_device.py
spinn_front_end_common/abstract_models/impl/__init__.py
spinn_front_end_common/abstract_models/impl/machine_data_specable_vertex.py
spinn_front_end_common/common_model_binaries/__init__.py
spinn_front_end_common/common_model_binaries/chip_power_monitor.aplx
spinn_front_end_common/common_model_binaries/command_sender_multicast_source.aplx
spinn_front_end_common/common_model_binaries/data_speed_up_packet_gatherer.aplx
spinn_front_end_common/common_model_binaries/extra_monitor_support.aplx
spinn_front_end_common/common_model_binaries/live_packet_gather.aplx
spinn_front_end_common/common_model_binaries/reverse_iptag_multicast_source.aplx
spinn_front_end_common/common_model_binaries/simple_pair_compressor.aplx
spinn_front_end_common/common_model_binaries/simple_unordered_compressor.aplx
spinn_front_end_common/data/__init__.py
spinn_front_end_common/data/fec_data_view.py
spinn_front_end_common/data/fec_data_writer.py
spinn_front_end_common/interface/__init__.py
spinnfrontendcommon-1!7.4.0.dist-info/licenses/LICENSE
spinnfrontendcommon-1!7.4.0.dist-info/licenses/LICENSE_POLICY.md
spinnfrontendcommon-1!7.4.0.dist-info/METADATA
spinnfrontendcommon-1!7.4.0.dist-info/WHEEL
spinnfrontendcommon-1!7.4.0.dist-info/entry_points.txt
spinnfrontendcommon-1!7.4.0.dist-info/top_level.txt
spinnfrontendcommon-1!7.4.0.dist-info/zip-safe
spinnfrontendcommon-1!7.4.0.dist-info/RECORD
