Metadata-Version: 2.4
Name: SpiNNFrontEndCommon
Version: 1!7.4.0
Summary: Common SpiNNaker Front end functions
Home-page: https://github.com/SpiNNakerManchester/SpiNNFrontEndCommon
Maintainer: SpiNNakerTeam
Maintainer-email: spinnakerusers@googlegroups.com
License: Apache-2.0
Keywords: spinnaker
Classifier: Development Status :: 5 - Production/Stable
Classifier: Intended Audience :: Developers
Classifier: Intended Audience :: Science/Research
Classifier: Natural Language :: English
Classifier: Operating System :: POSIX :: Linux
Classifier: Operating System :: Microsoft :: Windows
Classifier: Operating System :: MacOS
Classifier: Programming Language :: Python :: 3
Classifier: Programming Language :: Python :: 3.8
Classifier: Programming Language :: Python :: 3.9
Classifier: Programming Language :: Python :: 3.10
Classifier: Programming Language :: Python :: 3.11
Classifier: Programming Language :: Python :: 3.12
Classifier: Programming Language :: Python :: 3.13
Requires-Python: <4,>=3.8
License-File: LICENSE
License-File: LICENSE_POLICY.md
Requires-Dist: SpiNNMan==1!7.4.0
Requires-Dist: SpiNNaker_PACMAN==1!7.4.0
Requires-Dist: spalloc==1!7.4.0
Requires-Dist: scipy>=0.16.0
Provides-Extra: test
Requires-Dist: pytest-cov; extra == "test"
Requires-Dist: testfixtures; extra == "test"
Requires-Dist: httpretty!=1.0.0; extra == "test"
Requires-Dist: types-jsonschema; extra == "test"
Requires-Dist: types-requests; extra == "test"
Provides-Extra: plotting
Requires-Dist: seaborn; extra == "plotting"
Dynamic: license-file
